conflict_collection/__init__.py
conflict_collection/collectors/__init__.py
conflict_collection/collectors/conflict_type/__init__.py
conflict_collection/collectors/conflict_type/_git_ops.py
conflict_collection/collectors/conflict_type/collector.py
conflict_collection/collectors/societal/__init__.py
conflict_collection/collectors/societal/_git_ops.py
conflict_collection/collectors/societal/collector.py
conflict_collection/metrics/__init__.py
conflict_collection/metrics/anchored_ratio/__init__.py
conflict_collection/metrics/anchored_ratio/anchored_ratio.py
conflict_collection/schema/__init__.py
conflict_collection/schema/five_tuple.py
conflict_collection/schema/social_signals.py
conflict_collection/schema/typed_five_tuple.py
conflict_collection-0.0.2.dist-info/METADATA
conflict_collection-0.0.2.dist-info/WHEEL
conflict_collection-0.0.2.dist-info/licenses/LICENSE
conflict_collection-0.0.2.dist-info/RECORD
