Metadata-Version: 2.4
Name: conflict_collection
Version: 0.0.2
Summary: Data collection from Git merge conflicts.
Project-URL: Homepage, https://github.com/jinu-jang/conflict-collection
Project-URL: Repository, https://github.com/jinu-jang/conflict-collection.git
Project-URL: Issues, https://github.com/jinu-jang/conflict-collection/issues
Author: Jinu Jang
License-Expression: MIT
License-File: LICENSE
Keywords: conflict,git,merge,parser,version-control
Classifier: Development Status :: 4 - Beta
Classifier: Intended Audience :: Developers
Classifier: License :: OSI Approved :: MIT License
Classifier: Programming Language :: Python :: 3
Classifier: Programming Language :: Python :: 3.10
Classifier: Programming Language :: Python :: 3.11
Classifier: Programming Language :: Python :: 3.12
Classifier: Topic :: Software Development :: Libraries :: Python Modules
Classifier: Topic :: Software Development :: Version Control :: Git
Classifier: Topic :: Text Processing :: Filters
Requires-Python: >=3.10
Requires-Dist: conflict-parser
Requires-Dist: gitpython
Requires-Dist: pydantic
Requires-Dist: python-levenshtein
Provides-Extra: dev
Requires-Dist: black; extra == 'dev'
Requires-Dist: isort; extra == 'dev'
Requires-Dist: pytest; extra == 'dev'
Provides-Extra: docs
Requires-Dist: mkdocs; extra == 'docs'
Requires-Dist: mkdocs-material; extra == 'docs'
Requires-Dist: mkdocstrings[python]; extra == 'docs'
